Metadata-Version: 2.1
Name: temp-email
Version: 0.2
Summary: Wrapper for online service which provides temporary email address: https://www.1secmail.com/api/
Home-page: https://github.com/leirons/TempMail
Author: Ivan Grechka
Author-email: grecigor11@gmail.com
License: MIT
Keywords: temporary temp mail email address wrapper api anon anonymous secure free disposable
Platform: UNKNOWN
Classifier: Development Status :: 5 - Production/Stable
Classifier: Intended Audience :: Developers
Classifier: Operating System :: OS Independent
Classifier: Programming Language :: Python
Classifier: Programming Language :: Python :: 3.8
Classifier: Topic :: Internet :: WWW/HTTP
